sram.v
//latches: sr,d
//ffs: d,de,dr,sr,t,jk
`timescale 1ns/1ns

//sr
module sr(
    input clk,set,rst,
    output reg q
);

always @ * begin
    if(clk) begin
        case({set,rst})
            2'b01 : q <= 1'b0;
            2'b10 : q <= 1'b1;
        endcase
    end
end

endmodule
//sr_tb
module sr_tb(
    output reg clk,set,rst,
    output q
);

sr cut(.clk(clk),.set(set),.rst(rst),.q(q));

initial $dumpvars(0,sr_tb);

initial begin
    clk = 1'b0;
    repeat (10)
    #50 clk = ~clk;
end

initial begin
    set = 1'b0;
    #60 set = 1'b1;
    #30 set = 1'b0;
    #50 set = 1'b1;
    #130 set = 1'b0;
    #70 set = 1'b1;
    #70 set = 1'b0;
    #60 set = 1'b1;
end

initial begin
    rst = 1'b1;
    #60 rst = 1'b0;
    #30 rst = 1'b1;
    #50 rst = 1'b0;
    #130 rst = 1'b1;
    #70 rst = 1'b0;
    #70 rst = 1'b1;
    #60 rst = 1'b0;
end

endmodule

//d
module d(
    input clk,d,
    output reg q
);

always @ * begin
    if(clk) q <= d;
end

endmodule
//d_tb
module d_tb(
    output reg clk,d,
    output q
);

d cut(.clk(clk),.d(d),.q(q));

initial $dumpvars(0,d_tb);

initial begin
    clk = 1'b0;
    repeat (10)
    #50 clk = ~clk;
end

initial begin
    d = 1'b0;
    #60 d = 1'b1;
    #30 d = 1'b0;
    #50 d = 1'b1;
    #130 d = 1'b0;
    #70 d = 1'b1;
    #70 d = 1'b0;
    #60 d = 1'b1;
end

endmodule

//ff_d
module ff_d(
    input clk,d,
    output reg q
);

initial q = 1'b0;

always @(posedge clk) q <= d;

endmodule
//ff_d_tb
module ff_d_tb(
    output reg clk,d,
    output q
);

ff_d cut(.clk(clk),.d(d),.q(q));

initial $dumpvars(0,ff_d_tb);

initial begin
    clk = 1'd0;
    repeat (10)
    #50 clk = ~clk;
end

initial begin
    d = 1'd0;
    #60 d = 1'd1;
    #30 d = 1'd0;
    #50 d = 1'd1;
    #70 d = 1'd0;
    #150 d = 1'd1;
    #50 d = 1'd0;
    #50 d = 1'd1;
end

endmodule

//ff_d_en
module ff_d_en(
    input clk,en,d,
    output reg q
);

always @(posedge clk) begin
    if(en) q <= d;
end

endmodule
//ff_d_en_tb
module ff_d_en_tb(
    output reg clk,en,d,
    output q
);

ff_d_en cut(.clk(clk),.en(en),.d(d),.q(q));

initial $dumpvars(0,ff_d_en_tb);

initial begin
    clk = 1'd0;
    repeat (10)
    #50 clk = ~clk;
end

initial begin
    d = 1'd0;
    #60 d = 1'd1;
    #30 d = 1'd0;
    #50 d = 1'd1;
    #70 d = 1'd0;
    #150 d = 1'd1;
    #50 d = 1'd0;
    #30 d = 1'd1;
end

initial begin
    en = 1'd1;
    #350 en = 1'd0;
    #450 en = 1'd1;
end

endmodule

//d_r
module ff_d_r(
    input clk,d,rst,
    output reg q
);

always @(posedge clk or posedge rst) begin
    if(rst) q <= 1'b0;
    else q <= d;
end

endmodule
//d_r_tb
module ff_d_r_tb(
    output reg clk,d,rst,
    output q
);

ff_d_r cut(.clk(clk),.d(d),.rst(rst),.q(q));

initial $dumpvars(0,ff_d_r_tb);

initial begin
    clk = 1'd0;
    repeat (10)
    #50 clk = ~clk;
end

initial begin
    d = 1'd0;
    #60 d = 1'd1;
    #30 d = 1'd0;
    #50 d = 1'd1;
    #70 d = 1'd0;
    #150 d = 1'd1;
    #50 d = 1'd0;
    #50 d = 1'd1;
end

initial begin
    rst = 1'd1;
    #50 rst = 1'd0;
    #180 rst = 1'd1;
    #10 rst = 1'd0;
end

endmodule

//sr
module ff_sr(
    input clk,set,rst,
    output reg q
);

always @(posedge clk) begin
    if(set && !rst) q <= 1'd1;
    else if(!set && rst) q <= 1'd0;
end

endmodule
//sr_tb
module ff_sr_tb(
    output reg clk,set,rst,
    output q
);

ff_sr cut(.clk(clk),.set(set),.rst(rst),.q(q));

initial $dumpvars(0,ff_sr_tb);

initial begin
    clk = 1'd0;
    repeat (10)
    #50 clk = ~clk;
end

initial begin
    set = 1'd0;
    #60 set = 1'd1;
    #30 set = 1'd0;
    #50 set = 1'd1;
    #70 set = 1'd0;
    #150 set = 1'd1;
    #50 set = 1'd0;
    #50 set = 1'd1;
end

initial begin
    rst = 1'd1;
    #60 rst = 1'd0;
    #30 rst = 1'd1;
    #50 rst = 1'd0;
    #70 rst = 1'd1;
    #150 rst = 1'd0;
    #50 rst = 1'd1;
    #50 rst = 1'd0;
end

endmodule

//t
module ff_t(
    input clk,toggle,
    output reg q
);

initial q = 0;

always @(posedge clk) begin
    if(toggle) q <= ~q;
    else q <= q;
end

endmodule
//t_tb
module ff_t_tb(
    output reg clk,toggle,
    output q
);

ff_t cut(.clk(clk),.toggle(toggle),.q(q));

initial $dumpvars(0,ff_t_tb);

initial begin
    clk = 1'd0;
    repeat (10)
    #50 clk = ~clk;
end

initial begin
    toggle = 1'd0;
    #60 toggle = 1'd1;
    #30 toggle = 1'd0;
    #50 toggle = 1'd1;
    #70 toggle = 1'd0;
    #120 toggle = 1'd1;
    #50 toggle = 1'd0;
    #50 toggle = 1'd1;
end

endmodule

//ff_jk
module ff_jk(
    input clk,j,k,
    output reg q
);

always @(posedge clk) begin
    case({k,j})
        2'b00 : q <= q;
        2'b01 : q <= 1'b1;
        2'b10 : q <= 1'b0;
        2'b11 : q <= ~q;
    endcase
end 

endmodule
//ff_jk_tb
module ff_jk_tb(
    output reg clk,j,k,
    output q
);

ff_jk cut(.clk(clk),.j(j),.k(k),.q(q));

initial $dumpvars(0,ff_jk_tb);

initial begin
    clk = 1'd0;
    repeat (10)
    #50 clk = ~clk;
end

initial begin
    j = 1'd0;
    #60 j = 1'd1;
    #30 j = 1'd0;
    #50 j = 1'd1;
    #70 j = 1'd0;
    #150 j = 1'd1;
    #50 j = 1'd0;
    #50 j = 1'd1;
end

initial begin
    k = 1'd1;
    #60 k = 1'd0;
    #30 k = 1'd1;
    #50 k = 1'd0;
    #70 k = 1'd1;
    #150 k = 1'd0;
    #50 k = 1'd1;
    #50 k = 1'd0;
end

endmodule

//sa se proiecteze un bistabil cu validare folosind
//un multiplexor de 2:1 si un bistabil D

//multiplexor 2:1
module mux2_1(
    input sel,
    input [1:0] in,
    output reg o
);

always @ * o = in[sel];

endmodule
//tb multiplexor 2:1
module mux2_1_tb(
    output reg sel,
    output reg [1:0] in,
    output o
);

mux2_1 cut(.sel(sel),.in(in),.o(o));

integer i;

initial $dumpvars(0,mux2_1_tb);

initial begin
    for(i = 0;i < 8;i = i + 1)
       #100 {in,sel} = i; 
end

endmodule

//circuit ce foloseste mux2_1 si ff_d
module d_en(
    input clk,d,en,
    output o
);

wire f,g;

mux2_1 i0(.sel(en),.in({d,f}),.o(g));
ff_d i1(.clk(clk),.d(g),.q(f));

assign o = f;

endmodule
//tb circuit
module d_en_tb(
    output reg clk,d,en,
    output o
);

d_en cut(.clk(clk),.d(d),.en(en),.o(o));

initial $dumpvars(0,d_en_tb);

initial begin
    clk = 1'd0;
    repeat (10)
    #50 clk = ~clk;
end

initial begin
    d = 1'd0;
    #60 d = 1'd1;
    #30 d = 1'd0;
    #50 d = 1'd1;
    #70 d = 1'd0;
    #150 d = 1'd1;
    #50 d = 1'd0;
    #30 d = 1'd1;
end

initial begin
    en = 1'd1;
    #350 en = 1'd0;
    #450 en = 1'd1;
end

endmodule

//implementarea latchurilor rs cu porti
//implementare poarta nor
module sau_nu(input x,y,output reg z); 
always @ * z = ~ (x | y);
endmodule
//immplementare latch
module sr_gates(
    input s,r,
    output reg q,q_bar
);
initial q = 1'd0;
initial q = 1'd1;
wire f,g;
sau_nu i0(.x(r),.y(g),.z(f));
sau_nu i1(.x(s),.y(f),.z(g));
always @ * begin
    q = f;
    q_bar = g;
end
endmodule
//tb pentru latchurile rs cu porti
module sr_gates_tb(
    output reg s,r,
    output q,q_bar
);

sr_gates cut(.s(s),.r(r),.q(q),.q_bar(q_bar));

initial $dumpvars(0,sr_gates_tb);

initial begin
    {s,r} = 2'b01;
    #50 {s,r} = 2'b10;
    #50 {s,r} = 2'b01;
    #50 {s,r} = 2'b00;
    #50 {s,r} = 2'b11;//stare interzisa
end

endmodule


//multiple of 3
module mul_3(
    input clk,in,
    output reg out
);

reg f;
wire g,h;

always @ * begin
    f = in & ~ (g | h);
    out = in | g | h;
end

ff_d i0(.clk(clk),.d(f),.q(g));
ff_d i1(.clk(clk),.d(g),.q(h));

endmodule
//tb mul_3
module mul_3_tb(
    output reg clk,in,
    output out
);

mul_3 cut(.clk(clk),.in(in),.out(out));

initial $dumpvars(0,mul_3_tb);

initial begin
    clk = 1'd1;
    repeat (30)
    #50 clk = ~ clk;
end

initial begin
    in = 1'd0;
    #101 in = 1'd1;
    #101 in = 1'd0;
    #301 in = 1'd1;
    #201 in = 1'd0;
    #301 in = 1'd1;
    #301 in = 1'd0;
end

endmodule

dump.vcd
$date
	Tue Nov 24 15:01:35 2020
$end
$version
	Icarus Verilog
$end
$timescale
	1ns
$end
$scope module d_en_tb $end
$var wire 1 ! o $end
$var reg 1 " clk $end
$var reg 1 # d $end
$var reg 1 $ en $end
$scope module cut $end
$var wire 1 " clk $end
$var wire 1 # d $end
$var wire 1 $ en $end
$var wire 1 ! o $end
$var wire 1 % g $end
$var wire 1 & f $end
$scope module i0 $end
$var wire 2 ' in [1:0] $end
$var wire 1 $ sel $end
$var reg 1 % o $end
$upscope $end
$scope module i1 $end
$var wire 1 " clk $end
$var wire 1 % d $end
$var reg 1 & q $end
$upscope $end
$upscope $end
$upscope $end
$scope module d_tb $end
$var wire 1 ( q $end
$var reg 1 ) clk $end
$var reg 1 * d $end
$scope module cut $end
$var wire 1 ) clk $end
$var wire 1 * d $end
$var reg 1 ( q $end
$upscope $end
$upscope $end
$scope module ff_d_en_tb $end
$var wire 1 + q $end
$var reg 1 , clk $end
$var reg 1 - d $end
$var reg 1 . en $end
$scope module cut $end
$var wire 1 , clk $end
$var wire 1 - d $end
$var wire 1 . en $end
$var reg 1 + q $end
$upscope $end
$upscope $end
$scope module ff_d_r_tb $end
$var wire 1 / q $end
$var reg 1 0 clk $end
$var reg 1 1 d $end
$var reg 1 2 rst $end
$scope module cut $end
$var wire 1 0 clk $end
$var wire 1 1 d $end
$var wire 1 2 rst $end
$var reg 1 / q $end
$upscope $end
$upscope $end
$scope module ff_d_tb $end
$var wire 1 3 q $end
$var reg 1 4 clk $end
$var reg 1 5 d $end
$scope module cut $end
$var wire 1 4 clk $end
$var wire 1 5 d $end
$var reg 1 3 q $end
$upscope $end
$upscope $end
$scope module ff_jk_tb $end
$var wire 1 6 q $end
$var reg 1 7 clk $end
$var reg 1 8 j $end
$var reg 1 9 k $end
$scope module cut $end
$var wire 1 7 clk $end
$var wire 1 8 j $end
$var wire 1 9 k $end
$var reg 1 6 q $end
$upscope $end
$upscope $end
$scope module ff_sr_tb $end
$var wire 1 : q $end
$var reg 1 ; clk $end
$var reg 1 < rst $end
$var reg 1 = set $end
$scope module cut $end
$var wire 1 ; clk $end
$var wire 1 < rst $end
$var wire 1 = set $end
$var reg 1 : q $end
$upscope $end
$upscope $end
$scope module ff_t_tb $end
$var wire 1 > q $end
$var reg 1 ? clk $end
$var reg 1 @ toggle $end
$scope module cut $end
$var wire 1 ? clk $end
$var wire 1 @ toggle $end
$var reg 1 > q $end
$upscope $end
$upscope $end
$scope module mul_3_tb $end
$var wire 1 A out $end
$var reg 1 B clk $end
$var reg 1 C in $end
$scope module cut $end
$var wire 1 B clk $end
$var wire 1 C in $end
$var wire 1 D h $end
$var wire 1 E g $end
$var reg 1 F f $end
$var reg 1 A out $end
$scope module i0 $end
$var wire 1 B clk $end
$var wire 1 F d $end
$var reg 1 E q $end
$upscope $end
$scope module i1 $end
$var wire 1 B clk $end
$var wire 1 E d $end
$var reg 1 D q $end
$upscope $end
$upscope $end
$upscope $end
$scope module mux2_1_tb $end
$var wire 1 G o $end
$var reg 2 H in [1:0] $end
$var reg 1 I sel $end
$var integer 32 J i [31:0] $end
$scope module cut $end
$var wire 2 K in [1:0] $end
$var wire 1 I sel $end
$var reg 1 G o $end
$upscope $end
$upscope $end
$scope module sr_gates_tb $end
$var wire 1 L q_bar $end
$var wire 1 M q $end
$var reg 1 N r $end
$var reg 1 O s $end
$scope module cut $end
$var wire 1 N r $end
$var wire 1 O s $end
$var wire 1 P g $end
$var wire 1 Q f $end
$var reg 1 M q $end
$var reg 1 L q_bar $end
$scope module i0 $end
$var wire 1 N x $end
$var wire 1 P y $end
$var reg 1 Q z $end
$upscope $end
$scope module i1 $end
$var wire 1 O x $end
$var wire 1 Q y $end
$var reg 1 P z $end
$upscope $end
$upscope $end
$upscope $end
$scope module sr_tb $end
$var wire 1 R q $end
$var reg 1 S clk $end
$var reg 1 T rst $end
$var reg 1 U set $end
$scope module cut $end
$var wire 1 S clk $end
$var wire 1 T rst $end
$var wire 1 U set $end
$var reg 1 R q $end
$upscope $end
$upscope $end
$enddefinitions $end
#0
$dumpvars
0U
1T
0S
xR
0Q
1P
0O
1N
0M
1L
bx K
b0 J
xI
bx H
xG
0F
0E
0D
0C
1B
0A
0@
0?
0>
0=
1<
0;
x:
19
08
07
x6
05
04
03
12
01
00
0/
1.
0-
0,
x+
0*
0)
x(
b0 '
0&
0%
1$
0#
0"
0!
$end
#50
0R
0:
06
0+
0(
0L
1M
1Q
0P
1S
1O
0N
0B
1?
1;
17
14
02
10
1,
1)
1"
#60
1R
1(
1%
0T
1U
1@
0<
1=
09
18
15
11
1-
1*
b10 '
1#
#90
0R
0(
0%
1T
0U
0@
1<
0=
19
08
05
01
0-
0*
b0 '
0#
#100
1L
0M
1P
0Q
0G
0S
0O
1N
1B
0?
0;
07
04
00
0,
0)
0"
b1 J
b0 H
b0 K
0I
#101
1A
1F
1C
#140
1%
0T
1U
1@
0<
1=
09
18
15
11
1-
1*
b10 '
1#
#150
1R
1>
1:
16
13
1/
1+
1(
b11 '
1!
1&
1S
0N
0B
1?
1;
17
14
10
1,
1)
1"
#200
0F
1E
0L
0P
0S
1O
1N
1B
0?
0;
07
04
00
0,
0)
0"
b10 J
1I
#202
0C
#210
0%
0@
1<
0=
19
08
05
01
0-
b1 '
0#
#230
0/
12
#240
02
#250
0:
06
03
0+
b0 '
0!
0&
1S
0B
1?
1;
17
14
10
1,
1)
1"
#270
0R
0(
1T
0U
0*
#300
1D
0E
1G
0S
1B
0?
0;
07
04
00
0,
0)
0"
b11 J
b1 H
b1 K
0I
#330
1@
#340
0T
1U
1*
#350
1R
0>
1(
1S
0B
1?
1;
17
14
10
1,
1)
1"
0.
0$
#360
0<
1=
09
18
15
11
1-
b10 '
1#
#380
0@
#400
0A
0D
0G
0S
1B
0?
0;
07
04
00
0,
0)
0"
b100 J
1I
#410
1<
0=
19
08
05
01
0-
b0 '
0#
1T
0U
0*
#430
1@
#440
1-
b10 '
1#
#450
0R
1>
0(
1S
0B
1?
1;
17
14
10
1,
1)
1"
#460
0<
1=
09
18
15
11
#470
1R
1(
0T
1U
1*
#500
0S
1B
0?
0;
07
04
00
0,
0)
0"
b101 J
b10 H
b10 K
0I
#503
1A
1F
1C
#550
0B
#600
0F
1E
1G
1B
b110 J
1I
#650
0B
#700
1D
0E
1B
b111 J
b11 H
b11 K
0I
#704
0C
#750
0B
#800
0A
0D
1%
1B
b1000 J
1I
1.
1$
#850
0B
#900
1B
#950
0B
#1000
1B
#1005
1A
1F
1C
#1050
0B
#1100
0F
1E
1B
#1150
0B
#1200
0E
1D
1B
#1250
0B
#1300
1F
0D
1B
#1306
0A
0F
0C
